pyhadoopapi/__init__.py
pyhadoopapi/__main__.py
pyhadoopapi/client.py
pyhadoopapi/cluster.py
pyhadoopapi/cluster_command.py
pyhadoopapi/hdfs_command.py
pyhadoopapi/oozie.py
pyhadoopapi/oozie_command.py
pyhadoopapi/submit_command.py
pyhadoopapi/webhdfs.py
pyhadoopapi/apps/monitor/__main__.py
pyhadoopapi/apps/monitor/api.py
pyhadoopapi/apps/monitor/app.py
pyhadoopapi/apps/monitor/views.py
pyhadoopapi/apps/monitor/assets/css/c3.min.css
pyhadoopapi/apps/monitor/assets/css/main.css
pyhadoopapi/apps/monitor/assets/js/c3.min.js
pyhadoopapi/apps/monitor/assets/js/d3.min.js
pyhadoopapi/apps/monitor/assets/js/queues.js
pyhadoopapi/apps/monitor/templates/base.html
pyhadoopapi/apps/monitor/templates/cluster.html
pyhadoopapi/apps/tracker/__init__.py
pyhadoopapi/apps/tracker/__main__.py
pyhadoopapi/apps/tracker/api.py
pyhadoopapi/apps/tracker/service.py
pyhadoopapi/apps/tracker/tasks.py
pyhadoopapi/apps/tracker/views.py
pyhadoopapi/apps/tracker/assets/css/c3.min.css
pyhadoopapi/apps/tracker/assets/css/main.css
pyhadoopapi/apps/tracker/assets/js/c3.min.js
pyhadoopapi/apps/tracker/assets/js/d3.min.js
pyhadoopapi/apps/tracker/assets/js/queues.js
pyhadoopapi/apps/tracker/assets/js/tracking.js
pyhadoopapi/apps/tracker/templates/base.html
pyhadoopapi/apps/tracker/templates/cluster.html
pyox/__init__.py
pyox/__main__.py
pyox/client.py
pyox/cluster.py
pyox/cluster_command.py
pyox/hdfs_command.py
pyox/oozie.py
pyox/oozie_command.py
pyox/submit_command.py
pyox/webhdfs.py
pyox/apps/monitor/__main__.py
pyox/apps/monitor/api.py
pyox/apps/monitor/app.py
pyox/apps/monitor/views.py
pyox/apps/monitor/assets/css/c3.min.css
pyox/apps/monitor/assets/css/main.css
pyox/apps/monitor/assets/js/c3.min.js
pyox/apps/monitor/assets/js/d3.min.js
pyox/apps/monitor/assets/js/queues.js
pyox/apps/monitor/templates/base.html
pyox/apps/monitor/templates/cluster.html
pyox/apps/tracker/__init__.py
pyox/apps/tracker/__main__.py
pyox/apps/tracker/api.py
pyox-0.10.dist-info/METADATA
pyox-0.10.dist-info/RECORD
pyox-0.10.dist-info/WHEEL
pyox-0.10.dist-info/top_level.txt
